netdem/pynetdem.cpython-312-darwin.so
netdem/__init__.py
netdem/.dylibs/libopen-pal.40.dylib
netdem/.dylibs/libhwloc.15.dylib
netdem/.dylibs/libevent_pthreads-2.1.7.dylib
netdem/.dylibs/Python
netdem/.dylibs/libgfortran.5.dylib
netdem/.dylibs/libboost_math_tr1-mt.dylib
netdem/.dylibs/libmpi.40.dylib
netdem/.dylibs/libquadmath.0.dylib
netdem/.dylibs/libgcc_s.1.1.dylib
netdem/.dylibs/libopen-rte.40.dylib
netdem/.dylibs/libgmp.10.dylib
netdem/.dylibs/libmpfr.6.dylib
netdem/.dylibs/libevent_core-2.1.7.dylib
netdem-1.27.dist-info/RECORD
netdem-1.27.dist-info/WHEEL
netdem-1.27.dist-info/top_level.txt
netdem-1.27.dist-info/METADATA
