Metadata-Version: 2.1
Name: netdem
Version: 1.27
Summary: A neural network machine learning enabled DEM framework for computational particle mechanics.
Home-page: https://apaam.github.io/netdem_docs/
Author: APAAM
Author-email: lai.zhengshou@outlook.com
Requires-Dist: mpi4py
